{
    "projects": [
        {
            "id": 1,
            "smallImage": "images\/Picture7.jpg",
            "smallTitle": "fhxghxd",
            "smallText": "this is the small text",
            "largeImage": "images\/",
            "largeTitle": "fdsgfdshgsdf",
            "largeText": ""
        },
        {
            "id": 2,
            "smallImage": "images\/",
            "smallTitle": "fhxghxd",
            "smallText": "",
            "largeImage": "images\/",
            "largeTitle": "jhjgv",
            "largeText": ""
        }
    ]
}